node_vector_distance/__init__.py
node_vector_distance/correlation.py
node_vector_distance/data_preparation.py
node_vector_distance/distances.py
node_vector_distance/utils.py
node_vector_distance/variance.py
node_vector_distance-0.0.20.dist-info/METADATA
node_vector_distance-0.0.20.dist-info/WHEEL
node_vector_distance-0.0.20.dist-info/licenses/LICENSE
node_vector_distance-0.0.20.dist-info/RECORD
